nygame/__init__.py
nygame/_quietload.py
nygame/common.py
nygame/constants.py
nygame/digifont.py
nygame/font_cache.py
nygame/game.py
nygame/music.py
nygame/perf.py
nygame/time.py
nygame/utils.py
nygame/data/__init__.py
nygame/data/emojisets/__init__.py
nygame/emoji/__init__.py
nygame/emoji/emoji.py
nygame/emoji/emojiset.py
nygame/input/__init__.py
nygame/input/powermate.py
nygame-1.4.0.dist-info/LICENSE
nygame-1.4.0.dist-info/METADATA
nygame-1.4.0.dist-info/WHEEL
nygame-1.4.0.dist-info/top_level.txt
nygame-1.4.0.dist-info/zip-safe
nygame-1.4.0.dist-info/RECORD
