Metadata-Version: 2.1
Name: nygame
Version: 1.4.0
Summary: nygame
Home-page: UNKNOWN
Author: Natalie Fearnley
Author-email: nfearnley@gmail.com
License: MIT
Project-URL: Source, https://github.com/nfearnley/nygame
Project-URL: Tracker, https://github.com/nfearnley/nygame/issues
Keywords: game
Platform: any
Classifier: License :: OSI Approved :: MIT License
Classifier: Operating System :: OS Independent
Classifier: Programming Language :: Python :: 3
Requires-Python: >=3.8
License-File: LICENSE
Requires-Dist: pygame (==2.0.2)
Requires-Dist: emoji (==1.2.0)
Requires-Dist: nindex (==1.0.0)
Provides-Extra: dev
Requires-Dist: autopep8 (==1.5.5) ; extra == 'dev'
Requires-Dist: flake8 (==3.8.4) ; extra == 'dev'
Requires-Dist: pytest (==6.2.2) ; extra == 'dev'
